zzingestions/__init__.py
zzingestions/ingestion_job.py
zzingestions-1.3.3.2.dist-info/METADATA
zzingestions-1.3.3.2.dist-info/WHEEL
zzingestions-1.3.3.2.dist-info/licenses/LICENSE
zzingestions-1.3.3.2.dist-info/RECORD
