Metadata-Version: 2.4
Name: zzingestions
Version: 1.3.3.2
Summary: ZZIngestions is a powerful Python package that uses PySpark to transform data ingestion into a fluid and efficient process. It allows performing ETL operations in a scalable and intuitive way, improving the robustness and agility of data flows.
License: MIT
License-File: LICENSE
Author: ZZData Team
Author-email: zzdata@arezzo.com.br
Requires-Python: >=3.8
Classifier: License :: OSI Approved :: MIT License
Classifier: Programming Language :: Python :: 3
Classifier: Programming Language :: Python :: 3.8
Classifier: Programming Language :: Python :: 3.9
Classifier: Programming Language :: Python :: 3.10
Classifier: Programming Language :: Python :: 3.11
Classifier: Programming Language :: Python :: 3.12
Classifier: Programming Language :: Python :: 3.13
Classifier: Programming Language :: Python :: 3.14
Provides-Extra: aws
Provides-Extra: full
Provides-Extra: sap
Provides-Extra: spark
Requires-Dist: boto3 ; extra == "aws" or extra == "full"
Requires-Dist: botocore ; extra == "aws" or extra == "full"
Requires-Dist: databricks-sdk ; extra == "spark" or extra == "full"
Requires-Dist: great-expectations (==1.3.6)
Requires-Dist: ipython
Requires-Dist: pandas ; extra == "spark" or extra == "full"
Requires-Dist: pyrfc (==3.3.1) ; extra == "sap" or extra == "full"
Requires-Dist: pyspark ; extra == "spark" or extra == "full"
Requires-Dist: pytz ; extra == "spark" or extra == "full"
